{
"idle": {
	"nazwa": "Dzienna jazda",
	"opis": "Nudy..."
	"lokalizacjaIkony": "",
	"unikalnosc": "domyślny",
	"poziomNatezenia": "Niski",
	"czasTrwania": 0,
	"trybPracy": 0,
	"limitPolecen": 1,
	"zmiennaMinimalnegoOpoznienia": 5,
	"zmiennaMaksymalnegoOpoznienia": 10,
	"zmianaLiczbyPasazerow": 0,
     	"wagaPietraLosowanego": {
            "0": 1,
            "1": 1,
            "2": 1,
            "3": 1,
            "4": 1,
            "5": 1,
            "6": 1,
            "7": 1,
            "8": 1,
            "9": 1,
            "10": 1
        },
        "wagaPietraWybieranego": {
            "0": 5,
            "1": 1,
            "2": 1,
            "3": 1,
            "4": 1,
            "5": 1,
            "6": 1,
            "7": 1,
            "8": 1,
            "9": 1,
            "10": 1
        },
	"efektNaWinde": 0,
	"efektNaPojemnoscWindy": 0,
	"efektNaDrzwi": 0,
	"efektNaCierpliwoscPasazerow": 0
	},
"godziny_szczytu_w_dol": {
	"nazwa": "Godziny szczytu",
	"opis": "Z góry na dół...",
	"lokalizacjaIkony": "",
	"unikalnosc": "normalny",
	"poziomNatezenia": "Średni",
	"czasTrwania": 2,
	"trybPracy": 1,
	"limitPolecen": 5,
	"zmiennaMinimalnegoOpoznienia": 2,
	"zmiennaMaksymalnegoOpoznienia": 7,
	"zmianaLiczbyPasazerow": 0,
	"wagaPietraLosowanego": {
            "0": 1,
            "1": 1,
            "2": 1,
            "3": 1,
            "4": 3,
            "5": 4,
            "6": 5,
            "7": 6,
            "8": 7,
            "9": 7,
            "10": 7
        },
        "wagaPietraWybieranego": {
            "0": 7,
            "1": 1,
            "2": 1,
            "3": 1,
            "4": 1,
            "5": 1,
            "6": 1,
            "7": 1,
            "8": 1,
            "9": 1,
            "10": 1
        },
	"efektNaWinde": 0,
	"efektNaPojemnoscWindy": 0,
	"efektNaDrzwi": 0,
	"efektNaCierpliwoscPasazerow": 0
	},
"godziny_szczytu_w_gore": {
	"nazwa": "Godziny szczytu",
	"opis": "Z dołu na górę...",
	"lokalizacjaIkony": "",
	"unikalnosc": "normalny",
	"poziomNatezenia": "Średni",
	"czasTrwania": 2,
	"trybPracy": 1,
	"limitPolecen": 5,
	"zmiennaMinimalnegoOpoznienia": 2,
	"zmiennaMaksymalnegoOpoznienia": 7,
	"zmianaLiczbyPasazerow": 0,
	"wagaPietraLosowanego": {
            "0": 7,
            "1": 7,
            "2": 7,
            "3": 3,
            "4": 3,
            "5": 2,
            "6": 1,
            "7": 1,
            "8": 1,
            "9": 1,
            "10": 1
        },
        "wagaPietraWybieranego": {
            "0": 1,
            "1": 1,
            "2": 1,
            "3": 1,
            "4": 2,
            "5": 4,
            "6": 4,
            "7": 6,
            "8": 7,
            "9": 7,
            "10": 7
        },
	"efektNaWinde": 0,
	"efektNaPojemnoscWindy": 0,
	"efektNaDrzwi": 0,
	"efektNaCierpliwoscPasazerow": 0
	},
"godziny_szczytu_od_srodka": {
	"nazwa": "Atak na skrzydła",
	"opis": "Odwrót ze środka",
	"lokalizacjaIkony": "",
	"unikalnosc": "normalny",
	"poziomNatezenia": "Średni",
	"czasTrwania": 2,
	"trybPracy": 1,
	"limitPolecen": 5,
	"zmiennaMinimalnegoOpoznienia": 2,
	"zmiennaMaksymalnegoOpoznienia": 7,
	"zmianaLiczbyPasazerow": 0,
	"wagaPietraLosowanego": {
            "0": 1,
            "1": 1,
            "2": 1,
            "3": 3,
            "4": 7,
            "5": 7,
            "6": 7,
            "7": 3,
            "8": 1,
            "9": 1,
            "10": 1
        },
        "wagaPietraWybieranego": {
            "0": 7,
            "1": 4,
            "2": 2,
            "3": 1,
            "4": 1,
            "5": 1,
            "6": 1,
            "7": 1,
            "8": 2,
            "9": 4,
            "10": 7
        },
	"efektNaWinde": 0,
	"efektNaPojemnoscWindy": 0,
	"efektNaDrzwi": 0,
	"efektNaCierpliwoscPasazerow": 0
	},
"wielkie_grupy": {
	"nazwa": "W kupie siła",
	"opis": "Im więcej tym lepiej",
	"lokalizacjaIkony": "",
	"unikalnosc": "normalny",
	"poziomNatezenia": "Niski",
	"czasTrwania": 2,
	"trybPracy": 1,
	"limitPolecen": 3,
	"zmiennaMinimalnegoOpoznienia": 10,
	"zmiennaMaksymalnegoOpoznienia": 17,
	"zmianaLiczbyPasazerow": 5,
	"wagaPietraLosowanego": {
            "0": 1,
            "1": 1,
            "2": 1,
            "3": 1,
            "4": 1,
            "5": 1,
            "6": 1,
            "7": 1,
            "8": 1,
            "9": 1,
            "10": 1
        },
        "wagaPietraWybieranego": {
            "0": 7,
            "1": 1,
            "2": 1,
            "3": 1,
            "4": 1,
            "5": 1,
            "6": 1,
            "7": 1,
            "8": 1,
            "9": 1,
            "10": 1
        },
	"efektNaWinde": 0,
	"efektNaPojemnoscWindy": 0,
	"efektNaDrzwi": 0,
	"efektNaCierpliwoscPasazerow": 0
	},
"krytyczne_obciazenie_w_dol": {
	"nazwa": "Gorączka podróżna",
	"opis": "Zròbcie miejsce tam na dole..",
	"lokalizacjaIkony": "",
	"unikalnosc": "rzadki",
	"poziomNatezenia": "Wysoki",
	"czasTrwania": 2,
	"trybPracy": 1,
	"limitPolecen": 8,
	"zmiennaMinimalnegoOpoznienia": 2,
	"zmiennaMaksymalnegoOpoznienia": 7,
	"zmianaLiczbyPasazerow": 2,
	"wagaPietraLosowanego": {
            "0": 1,
            "1": 1,
            "2": 1,
            "3": 1,
            "4": 3,
            "5": 4,
            "6": 5,
            "7": 6,
            "8": 7,
            "9": 7,
            "10": 7
        },
        "wagaPietraWybieranego": {
            "0": 7,
            "1": 1,
            "2": 1,
            "3": 1,
            "4": 1,
            "5": 1,
            "6": 1,
            "7": 1,
            "8": 1,
            "9": 1,
            "10": 1
        },
	"efektNaWinde": 0,
	"efektNaPojemnoscWindy": 0,
	"efektNaDrzwi": 0,
	"efektNaCierpliwoscPasazerow": 0
	},
"krytyczne_obciazenie_w_gore": {
	"nazwa": "Gorączka podróżna",
	"opis": "Oby na gòrze bylo miejsce...",
	"lokalizacjaIkony": "",
	"unikalnosc": "rzadki",
	"poziomNatezenia": "Wysoki",
	"czasTrwania": 2,
	"trybPracy": 1,
	"limitPolecen": 8,
	"zmiennaMinimalnegoOpoznienia": 2,
	"zmiennaMaksymalnegoOpoznienia": 7,
	"zmianaLiczbyPasazerow": 2,
	"wagaPietraLosowanego": {
            "0": 7,
            "1": 7,
            "2": 7,
            "3": 3,
            "4": 3,
            "5": 2,
            "6": 1,
            "7": 1,
            "8": 1,
            "9": 1,
            "10": 1
        },
        "wagaPietraWybieranego": {
            "0": 1,
            "1": 1,
            "2": 1,
            "3": 1,
            "4": 2,
            "5": 4,
            "6": 4,
            "7": 6,
            "8": 7,
            "9": 7,
            "10": 7
        },
	"efektNaWinde": 0,
	"efektNaPojemnoscWindy": 0,
	"efektNaDrzwi": 0,
	"efektNaCierpliwoscPasazerow": 0
	}
}
